MANIFEST.in
setup.cfg
setup.py
pyvenom.egg-info/PKG-INFO
pyvenom.egg-info/SOURCES.txt
pyvenom.egg-info/dependency_links.txt
pyvenom.egg-info/entry_points.txt
pyvenom.egg-info/requires.txt
pyvenom.egg-info/top_level.txt
tests/__init__.py
tests/appengine_config.py
tests/helper.py
tests/runner.py
tests/test_helper.py
tests/internal/__init__.py
tests/internal/test_hybrid_model.py
tests/internal/hybrid_model/__init__.py
tests/internal/hybrid_model/test_HybridDatastoreEntity.py
tests/internal/hybrid_model/test_HybridModel.py
tests/internal/hybrid_model/test_HybridSearchDocument.py
tests/model/__init__.py
tests/model/test_Properties.py
tests/model/test_migrate.py
tests/model/test_model.py
tests/model/test_query.py
venom/.DS_Store
venom/__init__.py
venom/__init__.pyc
venom/__ui__.py
venom/__ui__.pyc
venom/vendor.pyc
venom/wsgi_entry.pyc
venom/internal/__init__.py
venom/internal/__init__.pyc
venom/internal/builtin_file.py
venom/internal/builtin_file.pyc
venom/internal/hybrid_model.py
venom/internal/hybrid_model.pyc
venom/internal/index_yaml.py
venom/internal/index_yaml.pyc
venom/internal/search_yaml.py
venom/internal/search_yaml.pyc
venom/internal/venom_yaml.pyc
venom/model/Properties.py
venom/model/Properties.pyc
venom/model/__init__.py
venom/model/__init__.pyc
venom/model/attribute.py
venom/model/attribute.pyc
venom/model/hybrid.pyc
venom/model/migrate.py
venom/model/migrate.pyc
venom/model/model.py
venom/model/model.pyc
venom/model/query.py
venom/model/query.pyc
venom/monkeypatches/.DS_Store
venom/monkeypatches/__init__.py
venom/monkeypatches/__init__.pyc
venom/monkeypatches/__json__.py
venom/monkeypatches/__json__.pyc
venom/monkeypatches/datetime_json.pyc
venom/routing/Parameters.py
venom/routing/Parameters.pyc
venom/routing/Protocols.py
venom/routing/Protocols.pyc
venom/routing/__init__.py
venom/routing/__init__.pyc
venom/routing/application.py
venom/routing/application.pyc
venom/routing/docs.py
venom/routing/docs.pyc
venom/routing/handlers.py
venom/routing/handlers.pyc
venom/routing/routes.py
venom/routing/routes.pyc
venom/routing/wsgi_entry.py
venom/routing/wsgi_entry.pyc
venom/routing/docs/index.html
venom/routing/docs/css/components/EndpointDoc.css
